quantarhei/__init__.py
quantarhei/lams.py
quantarhei/qrhei.py
quantarhei/builders/__init__.py
quantarhei/builders/aggregate_states.py
quantarhei/builders/aggregates.py
quantarhei/builders/disorder.py
quantarhei/builders/interactions.py
quantarhei/builders/modes.py
quantarhei/builders/molecules.py
quantarhei/builders/pdb.py
quantarhei/core/__init__.py
quantarhei/core/dfunction.py
quantarhei/core/frequency.py
quantarhei/core/implementations.py
quantarhei/core/managers.py
quantarhei/core/matrixdata.py
quantarhei/core/parallel.py
quantarhei/core/savable.py
quantarhei/core/scalar.py
quantarhei/core/singleton.py
quantarhei/core/stochastics.py
quantarhei/core/time.py
quantarhei/core/triangle.py
quantarhei/core/unique.py
quantarhei/core/units.py
quantarhei/core/valueaxis.py
quantarhei/core/wrappers.py
quantarhei/dev/__init__.py
quantarhei/dev/feature.py
quantarhei/implementations/__init__.py
quantarhei/implementations/aceto/__init__.py
quantarhei/implementations/cython/__init__.py
quantarhei/implementations/cython/redfield.py
quantarhei/implementations/python/__init__.py
quantarhei/implementations/python/redfield.py
quantarhei/models/__init__.py
quantarhei/models/bacteriochlorophylls.py
quantarhei/models/bacteriopheophitins.py
quantarhei/models/molecularmodel.py
quantarhei/models/spectdens.py
quantarhei/models/spectral_densities/__init__.py
quantarhei/models/spectral_densities/example_data_defined.py
quantarhei/models/spectral_densities/renger_2002.py
quantarhei/models/spectral_densities/wendling_2000.py
quantarhei/qm/__init__.py
quantarhei/qm/corfunctions/__init__.py
quantarhei/qm/corfunctions/cfmatrix.py
quantarhei/qm/corfunctions/correlationfunctions.py
quantarhei/qm/corfunctions/distributions.py
quantarhei/qm/corfunctions/spectraldensities.py
quantarhei/qm/hilbertspace/__init__.py
quantarhei/qm/hilbertspace/dmoment.py
quantarhei/qm/hilbertspace/evolutionoperator.py
quantarhei/qm/hilbertspace/hamiltonian.py
quantarhei-0.0.12.dist-info/DESCRIPTION.rst
quantarhei-0.0.12.dist-info/METADATA
quantarhei-0.0.12.dist-info/RECORD
quantarhei-0.0.12.dist-info/WHEEL
quantarhei-0.0.12.dist-info/entry_points.txt
quantarhei-0.0.12.dist-info/metadata.json
quantarhei-0.0.12.dist-info/top_level.txt
