Metadata-Version: 2.0
Name: quantarhei
Version: 0.0.12
Summary: Quantarhei: Open Quantum System Theory for Molecular Systems
Home-page: https://github.com/tmancal74/quantarhei
Author: Tomas Mancal
Author-email: mancal@karlov.mff.cuni.cz
License: MIT
Keywords: physics,chemistry,quantum mechanics,open quantum systems
Platform: UNKNOWN
Classifier: Development Status :: 3 - Alpha
Classifier: Intended Audience :: Science/Research
Classifier: Intended Audience :: Education
Classifier: Topic :: Scientific/Engineering :: Physics
Classifier: Topic :: Scientific/Engineering :: Chemistry
Classifier: License :: OSI Approved :: MIT License
Classifier: Programming Language :: Python :: 3
Classifier: Programming Language :: Python :: 3.3
Classifier: Programming Language :: Python :: 3.4
Classifier: Programming Language :: Python :: 3.5
Requires-Dist: matplotlib
Requires-Dist: numpy
Requires-Dist: scipy
